sahkon_hinta-1.0.2.dist-info/METADATA
sahkon_hinta-1.0.2.dist-info/WHEEL
sahkon_hinta-1.0.2.dist-info/entry_points.txt
sahkon_hinta/__init__.py
sahkon_hinta/main.py
sahkon_hinta-1.0.2.dist-info/RECORD
