Metadata-Version: 2.1
Name: sahkon-hinta
Version: 1.0.2
Summary: A CLI tool to get the current electricity price in Finland using sahko.tk
Keywords: electricity price finland sähkö hinta sähkön hinta sahko.tk
Author: elias-ka
Classifier: Development Status :: 5 - Production/Stable
Classifier: Topic :: Utilities
Classifier: Intended Audience :: End Users/Desktop
Classifier: License :: OSI Approved :: The Unlicense (Unlicense)
Classifier: Programming Language :: Python :: 3.10
Classifier: Programming Language :: Python :: 3.11
Classifier: Programming Language :: Python :: 3.12
Classifier: Programming Language :: Python :: 3.13
Requires-Python: >=3.10
Requires-Dist: playwright>=1.41.2
Requires-Dist: rich>=13.7.0
